README.txt
setup.py
autoupgrade3/__init__.py
autoupgrade3/version.py
autoupgrade3.egg-info/PKG-INFO
autoupgrade3.egg-info/SOURCES.txt
autoupgrade3.egg-info/dependency_links.txt
autoupgrade3.egg-info/requires.txt
autoupgrade3.egg-info/top_level.txt