Metadata-Version: 1.1
Name: autoupgrade3
Version: 0.2.1
Summary: Python 3 friendly automatic upgrade of python modules and packages
Home-page: https://github.com/hayorov/autoupgrade3
Author: Alexander Khaerov
Author-email: i@hayorov.ru
License: UNKNOWN
Platform: UNKNOWN
Classifier: Development Status :: 3 - Alpha
Classifier: Topic :: Utilities
Classifier: License :: OSI Approved :: MIT License
Classifier: Intended Audience :: Developers
Classifier: Operating System :: POSIX :: Linux
Classifier: Programming Language :: Python :: 2.7
Classifier: Programming Language :: Python :: 3.5
Classifier: Topic :: System :: Software Distribution
